Metadata-Version: 1.0
Name: Landonius13-distributions
Version: 0.1
Summary: Binomial and Gaussian distributions
Home-page: UNKNOWN
Author: Landon Settle
Author-email: settlelandon@yahoo.com
License: UNKNOWN
Platform: UNKNOWN
